omni_article_markdown/__init__.py
omni_article_markdown/cli.py
omni_article_markdown/extractor.py
omni_article_markdown/hookspecs.py
omni_article_markdown/omni_article_md.py
omni_article_markdown/parser.py
omni_article_markdown/plugins.py
omni_article_markdown/readers.py
omni_article_markdown/store.py
omni_article_markdown/utils.py
omni_article_markdown/extractors/163.py
omni_article_markdown/extractors/aliyun_developer.py
omni_article_markdown/extractors/appledev.py
omni_article_markdown/extractors/cf_blog.py
omni_article_markdown/extractors/cnblog.py
omni_article_markdown/extractors/freedium.py
omni_article_markdown/extractors/hugo.py
omni_article_markdown/extractors/infoq.py
omni_article_markdown/extractors/infoqcn.py
omni_article_markdown/extractors/jianshu.py
omni_article_markdown/extractors/juejin.py
omni_article_markdown/extractors/medium.py
omni_article_markdown/extractors/microsoft_learn.py
omni_article_markdown/extractors/oschina.py
omni_article_markdown/extractors/quantamagazine.py
omni_article_markdown/extractors/sspai.py
omni_article_markdown/extractors/tencent_cloud.py
omni_article_markdown/extractors/toutiao.py
omni_article_markdown/extractors/wechat_gzh.py
omni_article_markdown/extractors/yuque.py
omni_article_markdown/extractors/zhihu.py
omni_article_markdown/libs/stealth.min.js
omni_article_markdown-0.1.9.dist-info/METADATA
omni_article_markdown-0.1.9.dist-info/WHEEL
omni_article_markdown-0.1.9.dist-info/entry_points.txt
omni_article_markdown-0.1.9.dist-info/licenses/LICENSE
omni_article_markdown-0.1.9.dist-info/RECORD
