Metadata-Version: 2.4
Name: omni-article-markdown
Version: 0.1.9
Summary: Easily convert web articles (blogs, news, documents, etc.) into Markdown format.
Project-URL: Homepage, https://github.com/caol64/omni-article-markdown
Author-email: Lei <caol64@gmail.com>
License-Expression: MIT
License-File: LICENSE
Classifier: Development Status :: 5 - Production/Stable
Classifier: Environment :: Console
Classifier: Intended Audience :: Developers
Classifier: Intended Audience :: End Users/Desktop
Classifier: License :: OSI Approved :: MIT License
Classifier: Natural Language :: English
Classifier: Operating System :: OS Independent
Classifier: Programming Language :: Python :: 3
Classifier: Programming Language :: Python :: 3.13
Classifier: Topic :: Text Processing :: Markup :: Markdown
Classifier: Topic :: Utilities
Requires-Python: >=3.13
Requires-Dist: beautifulsoup4>=4.13.4
Requires-Dist: click-default-group>=1.2.4
Requires-Dist: click>=8.2.0
Requires-Dist: html5lib>=1.1
Requires-Dist: pip
Requires-Dist: pluggy>=1.6.0
Requires-Dist: requests>=2.32.3
Provides-Extra: dev
Requires-Dist: pytest; extra == 'dev'
